pynnkit/DerivableFunction.py
pynnkit/__init__.py
pynnkit/Layers/ActivationLayer.py
pynnkit/Layers/BaseLayer.py
pynnkit/Layers/Construct.py
pynnkit/Layers/LossLayer.py
pynnkit/Layers/WeightLayer.py
pynnkit/Layers/WeightLayerTypes.py
pynnkit/Layers/__init__.py
pynnkit/Layers/Activation/Activation.py
pynnkit/Layers/Activation/ActivationTypes.py
pynnkit/Layers/Activation/__init__.py
pynnkit/Layers/Initializers/InitializerTypes.py
pynnkit/Layers/Initializers/Initializers.py
pynnkit/Layers/Initializers/__init__.py
pynnkit/Layers/Loss/Loss.py
pynnkit/Layers/Loss/LossTypes.py
pynnkit/Layers/Loss/__init__.py
pynnkit/MNIST/MNIST_Loader.py
pynnkit/MNIST/__init__.py
pynnkit/MNIST/archive/t10k-images.idx3-ubyte
pynnkit/MNIST/archive/t10k-labels.idx1-ubyte
pynnkit/MNIST/archive/train-images.idx3-ubyte
pynnkit/MNIST/archive/train-labels.idx1-ubyte
pynnkit/MNIST/archive/t10k-images-idx3-ubyte/t10k-images-idx3-ubyte
pynnkit/MNIST/archive/t10k-labels-idx1-ubyte/t10k-labels-idx1-ubyte
pynnkit/MNIST/archive/train-images-idx3-ubyte/train-images-idx3-ubyte
pynnkit/MNIST/archive/train-labels-idx1-ubyte/train-labels-idx1-ubyte
pynnkit/Networks/BaseNeuralNetwork.py
pynnkit/Networks/FeedForwardNeuralNetwork.py
pynnkit/Networks/__init__.py
pynnkit-1.0.5.data/data/pynnkit/MNIST/archive/t10k-images.idx3-ubyte
pynnkit-1.0.5.data/data/pynnkit/MNIST/archive/t10k-labels.idx1-ubyte
pynnkit-1.0.5.data/data/pynnkit/MNIST/archive/train-images.idx3-ubyte
pynnkit-1.0.5.data/data/pynnkit/MNIST/archive/train-labels.idx1-ubyte
pynnkit-1.0.5.data/data/pynnkit/MNIST/archive/t10k-images-idx3-ubyte/t10k-images-idx3-ubyte
pynnkit-1.0.5.data/data/pynnkit/MNIST/archive/t10k-labels-idx1-ubyte/t10k-labels-idx1-ubyte
pynnkit-1.0.5.data/data/pynnkit/MNIST/archive/train-images-idx3-ubyte/train-images-idx3-ubyte
pynnkit-1.0.5.data/data/pynnkit/MNIST/archive/train-labels-idx1-ubyte/train-labels-idx1-ubyte
pynnkit-1.0.5.dist-info/METADATA
pynnkit-1.0.5.dist-info/WHEEL
pynnkit-1.0.5.dist-info/top_level.txt
pynnkit-1.0.5.dist-info/RECORD
