Metadata-Version: 2.1
Name: pynnkit
Version: 1.0.5
Summary: Neural Network Kit
Home-page: UNKNOWN
Author: Paul Walcher
Author-email: paulwalcher12@gmail.com
License: UNKNOWN
Platform: UNKNOWN
Classifier: Programming Language :: Python :: 3
Classifier: License :: OSI Approved :: MIT License
Classifier: Operating System :: OS Independent
Requires-Python: >=3.6
Requires-Dist: numpy (>=1.26.2)
